parselinks/__init__.py
parselinks/cmdline.py
parselinks/fetcher.py
parselinks/linkparser.py
parselinks/parser.py
parselinks-0.0.1.dist-info/LICENSE
parselinks-0.0.1.dist-info/METADATA
parselinks-0.0.1.dist-info/WHEEL
parselinks-0.0.1.dist-info/top_level.txt
parselinks-0.0.1.dist-info/RECORD
