Metadata-Version: 2.1
Name: parselinks
Version: 0.0.1
Summary: Simple python module to extract links from pages.
Home-page: https://github.com/venins/pa
Author: vishal singh
Author-email: vishaldsingh06@gmail.com
License: UNKNOWN
Platform: UNKNOWN
Classifier: Programming Language :: Python :: 3
Classifier: License :: OSI Approved :: MIT License
Classifier: Operating System :: OS Independent
Requires-Dist: requests (==2.20.1)
Requires-Dist: lxml (==4.2.5)
